[
    {
        "type":"Biblioteca Estudios Previsional",
        "typeCode":"001",
        "data": [
          {
            "id":1,
            "title": "",            
            "description": "Una Mirada al Sistema de Pensiones Peruano al 2050 (2007)",
            "url": "BEP_001.pdf",
            "urlTitle": "Descargar"   
          },
          {
            "id":2,
            "title": "",            
            "description": "Informe Comisión Protección Social (2017)",
            "url": "BEP_002.pdf",
            "urlTitle": "Descargar"   
          },
          {
            "id":3,
            "title": "",            
            "description": "Diagnóstico del Sistema de Pensiones Peruano (2019) ",
            "url": "BEP_003.pdf",
            "urlTitle": "Descargar"   
          },
          {
            "id":4,
            "title": "",            
            "description": "Informality and the Challenge of Pension Adequacy: Outlook and Reform Options for Peru (2019)",
            "url": "BEP_004.pdf",
            "urlTitle": "Descargar"   
          },
          {
            "id":5,
            "title": "",            
            "description": "Informe Consejo Evaluador Pensiones (2019)",
            "url": "BEP_005.pdf",
            "urlTitle": "Descargar"   
          },
          {
            "id":6,
            "title": "",            
            "description": "Estudio Sistema de Pensiones de Perú (2019)",
            "url": "BEP_006.pdf",
            "urlTitle": "Descargar"   
          },
          {
            "id":7,
            "title": "",            
            "description": "Review of Pensions Systems Peru (2019)",
            "url": "BEP_007.pdf",
            "urlTitle": "Descargar"   
          },
          {
            "id":8,
            "title": "",            
            "description": "El Futuro de las Pensiones en el Perú (2020)",
            "url": "BEP_008.pdf",
            "urlTitle": "Descargar"   
          },
          {
            "id":9,
            "title": "",            
            "description": "Lineamientos Generales de la Reforma CEM (2020)",
            "url": "BEP_009.pdf",
            "urlTitle": "Descargar"   
          }       
        ]
      } 
    ]
